spoffy/__init__.py
spoffy/client/__init__.py
spoffy/client/base.py
spoffy/client/common.py
spoffy/exceptions.py
spoffy/io/__init__.py
spoffy/io/aiohttp.py
spoffy/io/requests.py
spoffy/models/__init__.py
spoffy/models/audiofeatures.py
spoffy/models/base.py
spoffy/models/collections.py
spoffy/models/compat.py
spoffy/models/core.py
spoffy/models/image.py
spoffy/models/library.py
spoffy/models/paging.py
spoffy/models/personalization.py
spoffy/models/player.py
spoffy/models/playlists.py
spoffy/models/recommendations.py
spoffy/models/search.py
spoffy/models/token.py
spoffy/models/users.py
spoffy/modules/__init__.py
spoffy/modules/apimodule.py
spoffy/modules/mixins.py
spoffy/modules/modules.py
spoffy/modules/sansio.py
spoffy/py.typed
spoffy/sansio.py
spoffy/spotify.py
spoffy/util.py
spoffy-1.0.1.dist-info/LICENSE
spoffy-1.0.1.dist-info/METADATA
spoffy-1.0.1.dist-info/WHEEL
spoffy-1.0.1.dist-info/RECORD
